tox_DEBIAN/__init__.py
tox_DEBIAN/install.py
tox_DEBIAN-0.3.dist-info/LICENSE
tox_DEBIAN-0.3.dist-info/METADATA
tox_DEBIAN-0.3.dist-info/WHEEL
tox_DEBIAN-0.3.dist-info/entry_points.txt
tox_DEBIAN-0.3.dist-info/top_level.txt
tox_DEBIAN-0.3.dist-info/RECORD
