Metadata-Version: 2.1
Name: tox-DEBIAN
Version: 0.3
Summary: debian package installer tox plugin
Home-page: UNKNOWN
License: MIT license
Platform: UNKNOWN
Classifier: Development Status :: 5 - Production/Stable
Classifier: Environment :: Plugins
Classifier: Framework :: tox
Classifier: Intended Audience :: Developers
Classifier: License :: OSI Approved :: MIT License
Classifier: Operating System :: OS Independent
Classifier: Programming Language :: Python :: 3
Classifier: Programming Language :: Python :: 3.5
Classifier: Programming Language :: Python :: 3.6
Classifier: Programming Language :: Python :: 3.7
Classifier: Topic :: Software Development :: Testing
Requires-Python: ~=3.5
Requires-Dist: tox (<4.0,>=3.0)
